<PAMDataset>
  <Metadata domain="Esri">
    <MDI key="PyramidResamplingType">NEAREST</MDI>
  </Metadata>
  <PAMRasterBand band="1">
    <Metadata>
      <MDI key="RepresentationType">ATHEMATIC</MDI>
      <MDI key="STATISTICS_COVARIANCES">59.72583390285129</MDI>
      <MDI key="STATISTICS_MAXIMUM">312.57000732422</MDI>
      <MDI key="STATISTICS_MEAN">288.23821097371</MDI>
      <MDI key="STATISTICS_MINIMUM">260.51000976563</MDI>
      <MDI key="STATISTICS_SKIPFACTORX">1</MDI>
      <MDI key="STATISTICS_SKIPFACTORY">1</MDI>
      <MDI key="STATISTICS_STDDEV">7.727977969589</MDI>
      <MDI key="STATISTICS_VALID_PERCENT">63.81</MDI>
    </Metadata>
  </PAMRasterBand>
</PAMDataset>
